mongo_tfrecords/__init__.py
mongo_tfrecords/__main__.py
mongo_tfrecords/exporter.py
mongo_tfrecords-0.0.2.dist-info/LICENSE
mongo_tfrecords-0.0.2.dist-info/METADATA
mongo_tfrecords-0.0.2.dist-info/WHEEL
mongo_tfrecords-0.0.2.dist-info/top_level.txt
mongo_tfrecords-0.0.2.dist-info/RECORD
