Metadata-Version: 2.1
Name: mongo-tfrecords
Version: 0.0.2
Summary: mongo-tfrecords - Library that exports mongodb data to tensorflow files (tf-record)
Home-page: https://github.com/felixfire/mongo-tfrecords
Author: Vadim Sharay
Author-email: vadimsharay@gmail.com
Maintainer: Vadim Sharay
Maintainer-email: vadimsharay@gmail.com
License: Apache License, Version 2.0
Keywords: export tensorflow mongodb python3
Platform: UNKNOWN
Classifier: Development Status :: 3 - Alpha
Classifier: License :: OSI Approved :: Apache Software License
Classifier: Operating System :: OS Independent
Classifier: Programming Language :: Python :: 3.5
Classifier: Programming Language :: Python :: 3.6
Classifier: Programming Language :: Python :: 3.7
Classifier: Programming Language :: Python :: Implementation :: PyPy
Classifier: Intended Audience :: Developers
Classifier: Topic :: Software Development :: Libraries :: Python Modules
Classifier: Topic :: Utilities
Requires-Python: >=3.5
Requires-Dist: pymongo (~=3.9)
Requires-Dist: tensorflow (~=2.3)
Requires-Dist: click (~=7.1)
Provides-Extra: dev
Requires-Dist: black (==19.10b0) ; extra == 'dev'
Requires-Dist: flake8-black (~=0.1) ; extra == 'dev'
Requires-Dist: flake8 (~=3.7) ; extra == 'dev'
Requires-Dist: pre-commit (~=1.20) ; extra == 'dev'
